LICENSE
MANIFEST.in
README.rst
boupy.py
setup.py
boupy.egg-info/PKG-INFO
boupy.egg-info/SOURCES.txt
boupy.egg-info/dependency_links.txt
boupy.egg-info/entry_points.txt
boupy.egg-info/not-zip-safe
boupy.egg-info/requires.txt
boupy.egg-info/top_level.txt
etc/config.json