Metadata-Version: 1.1
Name: boupy
Version: 0.1.1
Summary: Boupy help your life with file system backup to the cloud!
Home-page: https://github.com/yograterol/boupy
Author: Yohan Graterol
Author-email: y@mejorando.la | yograterol@fedoraproject.org
License: Copyright 2014 Yohan Graterol
